hexachromix/__init__.py
hexachromix/api.py
hexachromix/cli.py
hexachromix/core.cpython-39-darwin.so
hexachromix/core.pyx
hexachromix/tests/__init__.py
hexachromix/tests/test_core.py
hexachromix-0.2.5.dist-info/METADATA
hexachromix-0.2.5.dist-info/WHEEL
hexachromix-0.2.5.dist-info/entry_points.txt
hexachromix-0.2.5.dist-info/top_level.txt
hexachromix-0.2.5.dist-info/RECORD
