Metadata-Version: 2.1
Name: hexachromix
Version: 0.2.5
Summary: Hexachromix
Home-page: UNKNOWN
Author: Taylor Vance
Author-email: mirrors.cities0w@icloud.com
License: UNKNOWN
Platform: UNKNOWN
Requires-Dist: cython (<4.0.0)
Requires-Dist: multimcts (==0.6.4)
Requires-Dist: fastapi
Requires-Dist: uvicorn
Requires-Dist: psutil
